ctgenerics/__init__.py
ctgenerics/connect.py
ctgenerics/project_setup.py
tests/__init__.py
tests/connect_test.py
tests/intergration_test.py
ctgenerics-0.1.14.dist-info/LICENSE
ctgenerics-0.1.14.dist-info/METADATA
ctgenerics-0.1.14.dist-info/WHEEL
ctgenerics-0.1.14.dist-info/entry_points.txt
ctgenerics-0.1.14.dist-info/top_level.txt
ctgenerics-0.1.14.dist-info/RECORD
